{
  "type": "FeatureCollection",
  "name": "114081",
  "features": [
    {
      "type": "Feature",
      "geometry": {
        "type": "Point",
        "coordinates": [
          139.195005,
          36.117025
        ]
      },
      "properties": {
        "NO": 30034,
        "共通ID": "E1140800023201",
        "都道府県名及び市町村名": "埼玉県寄居町",
        "施設・場所名": "寄居町南口駅前拠点（Ｙｏｔｔｅｃｏ・ＹＯＲＩＢＡ）",
        "住所": "埼玉県寄居町大字寄居1231-11",
        "洪水": "1",
        "崖崩れ、土石流及び地滑り": "",
        "高潮": "",
        "地震": "1",
        "津波": "",
        "大規模な火事": "",
        "内水氾濫": "1",
        "火山現象": "",
        "指定避難所との住所同一": "",
        "備考": ""
      }
    },
    {
      "type": "Feature",
      "geometry": {
        "type": "Point",
        "coordinates": [
          139.187131,
          36.116096
        ]
      },
      "properties": {
        "NO": 30035,
        "共通ID": "E1140800003201",
        "都道府県名及び市町村名": "埼玉県寄居町",
        "施設・場所名": "寄居小学校",
        "住所": "埼玉県寄居町大字寄居206",
        "洪水": "1",
        "崖崩れ、土石流及び地滑り": "1",
        "高潮": "",
        "地震": "1",
        "津波": "",
        "大規模な火事": "",
        "内水氾濫": "",
        "火山現象": "",
        "指定避難所との住所同一": "1",
        "備考": ""
      }
    },
    {
      "type": "Feature",
      "geometry": {
        "type": "Point",
        "coordinates": [
          139.208012,
          36.127953
        ]
      },
      "properties": {
        "NO": 30036,
        "共通ID": "E1140800004201",
        "都道府県名及び市町村名": "埼玉県寄居町",
        "施設・場所名": "寄居中学校",
        "住所": "埼玉県寄居町大字桜沢2000",
        "洪水": "1",
        "崖崩れ、土石流及び地滑り": "1",
        "高潮": "",
        "地震": "1",
        "津波": "",
        "大規模な火事": "",
        "内水氾濫": "",
        "火山現象": "",
        "指定避難所との住所同一": "1",
        "備考": ""
      }
    },
    {
      "type": "Feature",
      "geometry": {
        "type": "Point",
        "coordinates": [
          139.20616,
          36.130697
        ]
      },
      "properties": {
        "NO": 30037,
        "共通ID": "E1140800006201",
        "都道府県名及び市町村名": "埼玉県寄居町",
        "施設・場所名": "桜沢小学校",
        "住所": "埼玉県寄居町大字桜沢2740",
        "洪水": "1",
        "崖崩れ、土石流及び地滑り": "1",
        "高潮": "",
        "地震": "1",
        "津波": "",
        "大規模な火事": "",
        "内水氾濫": "",
        "火山現象": "",
        "指定避難所との住所同一": "1",
        "備考": ""
      }
    },
    {
      "type": "Feature",
      "geometry": {
        "type": "Point",
        "coordinates": [
          139.20441,
          36.10511
        ]
      },
      "properties": {
        "NO": 30038,
        "共通ID": "E1140800010201",
        "都道府県名及び市町村名": "埼玉県寄居町",
        "施設・場所名": "城南中学校",
        "住所": "埼玉県寄居町大字鉢形2222",
        "洪水": "1",
        "崖崩れ、土石流及び地滑り": "1",
        "高潮": "",
        "地震": "1",
        "津波": "",
        "大規模な火事": "",
        "内水氾濫": "",
        "火山現象": "",
        "指定避難所との住所同一": "1",
        "備考": ""
      }
    },
    {
      "type": "Feature",
      "geometry": {
        "type": "Point",
        "coordinates": [
          139.204916,
          36.110872
        ]
      },
      "properties": {
        "NO": 30039,
        "共通ID": "E1140800011201",
        "都道府県名及び市町村名": "埼玉県寄居町",
        "施設・場所名": "鉢形小学校",
        "住所": "埼玉県寄居町大字鉢形645",
        "洪水": "1",
        "崖崩れ、土石流及び地滑り": "1",
        "高潮": "",
        "地震": "1",
        "津波": "",
        "大規模な火事": "",
        "内水氾濫": "",
        "火山現象": "",
        "指定避難所との住所同一": "1",
        "備考": ""
      }
    },
    {
      "type": "Feature",
      "geometry": {
        "type": "Point",
        "coordinates": [
          139.252353,
          36.108488
        ]
      },
      "properties": {
        "NO": 30040,
        "共通ID": "E1140800012201",
        "都道府県名及び市町村名": "埼玉県寄居町",
        "施設・場所名": "男衾小学校",
        "住所": "埼玉県寄居町大字富田53",
        "洪水": "1",
        "崖崩れ、土石流及び地滑り": "1",
        "高潮": "",
        "地震": "1",
        "津波": "",
        "大規模な火事": "",
        "内水氾濫": "",
        "火山現象": "",
        "指定避難所との住所同一": "1",
        "備考": ""
      }
    },
    {
      "type": "Feature",
      "geometry": {
        "type": "Point",
        "coordinates": [
          139.250664,
          36.108569
        ]
      },
      "properties": {
        "NO": 30041,
        "共通ID": "E1140800013201",
        "都道府県名及び市町村名": "埼玉県寄居町",
        "施設・場所名": "男衾中学校",
        "住所": "埼玉県寄居町大字富田65",
        "洪水": "1",
        "崖崩れ、土石流及び地滑り": "1",
        "高潮": "",
        "地震": "1",
        "津波": "",
        "大規模な火事": "",
        "内水氾濫": "",
        "火山現象": "",
        "指定避難所との住所同一": "1",
        "備考": ""
      }
    },
    {
      "type": "Feature",
      "geometry": {
        "type": "Point",
        "coordinates": [
          139.150624,
          36.104259
        ]
      },
      "properties": {
        "NO": 30042,
        "共通ID": "E1140800014201",
        "都道府県名及び市町村名": "埼玉県寄居町",
        "施設・場所名": "生涯学舎",
        "住所": "埼玉県寄居町大字風布212",
        "洪水": "1",
        "崖崩れ、土石流及び地滑り": "1",
        "高潮": "",
        "地震": "1",
        "津波": "",
        "大規模な火事": "",
        "内水氾濫": "",
        "火山現象": "",
        "指定避難所との住所同一": "1",
        "備考": ""
      }
    },
    {
      "type": "Feature",
      "geometry": {
        "type": "Point",
        "coordinates": [
          139.166609,
          36.119672
        ]
      },
      "properties": {
        "NO": 30043,
        "共通ID": "E1140800018201",
        "都道府県名及び市町村名": "埼玉県寄居町",
        "施設・場所名": "末野公園",
        "住所": "埼玉県寄居町大字末野971",
        "洪水": "1",
        "崖崩れ、土石流及び地滑り": "1",
        "高潮": "",
        "地震": "1",
        "津波": "",
        "大規模な火事": "",
        "内水氾濫": "",
        "火山現象": "",
        "指定避難所との住所同一": "",
        "備考": ""
      }
    },
    {
      "type": "Feature",
      "geometry": {
        "type": "Point",
        "coordinates": [
          139.206341,
          36.155022
        ]
      },
      "properties": {
        "NO": 30044,
        "共通ID": "E1140800020201",
        "都道府県名及び市町村名": "埼玉県寄居町",
        "施設・場所名": "用土小学校",
        "住所": "埼玉県寄居町大字用土2859",
        "洪水": "1",
        "崖崩れ、土石流及び地滑り": "1",
        "高潮": "",
        "地震": "1",
        "津波": "",
        "大規模な火事": "",
        "内水氾濫": "",
        "火山現象": "",
        "指定避難所との住所同一": "1",
        "備考": ""
      }
    },
    {
      "type": "Feature",
      "geometry": {
        "type": "Point",
        "coordinates": [
          139.188031,
          36.103126
        ]
      },
      "properties": {
        "NO": 30045,
        "共通ID": "E1140800022201",
        "都道府県名及び市町村名": "埼玉県寄居町",
        "施設・場所名": "折原小学校",
        "住所": "埼玉県寄居町大字立原385",
        "洪水": "1",
        "崖崩れ、土石流及び地滑り": "1",
        "高潮": "",
        "地震": "1",
        "津波": "",
        "大規模な火事": "",
        "内水氾濫": "",
        "火山現象": "",
        "指定避難所との住所同一": "1",
        "備考": ""
      }
    }
  ]
}