{
  "type": "FeatureCollection",
  "name": "184420",
  "features": [
    {
      "type": "Feature",
      "geometry": {
        "type": "Point",
        "coordinates": [
          135.946614,
          35.603162
        ]
      },
      "properties": {
        "NO": 34397,
        "共通ID": "E1844200001111",
        "都道府県名及び市町村名": "福井県美浜町",
        "施設・場所名": "美浜中央小学校",
        "住所": "福井県美浜町河原市8-2",
        "指定緊急避難場所との住所同一": "1",
        "その他市町村長が必要と認める事項": null,
        "受入対象者": null,
        "備考": ""
      }
    },
    {
      "type": "Feature",
      "geometry": {
        "type": "Point",
        "coordinates": [
          135.94656,
          35.602242
        ]
      },
      "properties": {
        "NO": 34398,
        "共通ID": "E1844200002121",
        "都道府県名及び市町村名": "福井県美浜町",
        "施設・場所名": "美浜町せせらぎ保育園",
        "住所": "福井県美浜町河原市8-8",
        "指定緊急避難場所との住所同一": "",
        "その他市町村長が必要と認める事項": null,
        "受入対象者": "要配慮者",
        "備考": ""
      }
    },
    {
      "type": "Feature",
      "geometry": {
        "type": "Point",
        "coordinates": [
          135.914117,
          35.602818
        ]
      },
      "properties": {
        "NO": 34399,
        "共通ID": "E1844200003111",
        "都道府県名及び市町村名": "福井県美浜町",
        "施設・場所名": "美浜町総合体育館",
        "住所": "福井県美浜町久々子26-30",
        "指定緊急避難場所との住所同一": "1",
        "その他市町村長が必要と認める事項": null,
        "受入対象者": null,
        "備考": ""
      }
    },
    {
      "type": "Feature",
      "geometry": {
        "type": "Point",
        "coordinates": [
          135.919972,
          35.602812
        ]
      },
      "properties": {
        "NO": 34400,
        "共通ID": "E1844200004121",
        "都道府県名及び市町村名": "福井県美浜町",
        "施設・場所名": "美浜町みずうみ保育園",
        "住所": "福井県美浜町久々子42-1-3",
        "指定緊急避難場所との住所同一": "",
        "その他市町村長が必要と認める事項": null,
        "受入対象者": "要配慮者",
        "備考": ""
      }
    },
    {
      "type": "Feature",
      "geometry": {
        "type": "Point",
        "coordinates": [
          135.941275,
          35.599846
        ]
      },
      "properties": {
        "NO": 34401,
        "共通ID": "E1844200006121",
        "都道府県名及び市町村名": "福井県美浜町",
        "施設・場所名": "美浜町保健福祉センター「はあとぴあ」",
        "住所": "福井県美浜町郷市25-20",
        "指定緊急避難場所との住所同一": "",
        "その他市町村長が必要と認める事項": null,
        "受入対象者": "要配慮者",
        "備考": ""
      }
    },
    {
      "type": "Feature",
      "geometry": {
        "type": "Point",
        "coordinates": [
          135.922929,
          35.602694
        ]
      },
      "properties": {
        "NO": 34402,
        "共通ID": "E1844200007111",
        "都道府県名及び市町村名": "福井県美浜町",
        "施設・場所名": "美浜西小学校",
        "住所": "福井県美浜町金山14-1",
        "指定緊急避難場所との住所同一": "1",
        "その他市町村長が必要と認める事項": null,
        "受入対象者": null,
        "備考": ""
      }
    },
    {
      "type": "Feature",
      "geometry": {
        "type": "Point",
        "coordinates": [
          135.983621,
          35.627773
        ]
      },
      "properties": {
        "NO": 34403,
        "共通ID": "E1844200008121",
        "都道府県名及び市町村名": "福井県美浜町",
        "施設・場所名": "美浜町あおなみ保育園",
        "住所": "福井県美浜町佐田62-43",
        "指定緊急避難場所との住所同一": "",
        "その他市町村長が必要と認める事項": null,
        "受入対象者": "要配慮者",
        "備考": ""
      }
    },
    {
      "type": "Feature",
      "geometry": {
        "type": "Point",
        "coordinates": [
          135.985332,
          35.628965
        ]
      },
      "properties": {
        "NO": 34404,
        "共通ID": "E1844200009111",
        "都道府県名及び市町村名": "福井県美浜町",
        "施設・場所名": "美浜東小学校",
        "住所": "福井県美浜町佐田69-4",
        "指定緊急避難場所との住所同一": "1",
        "その他市町村長が必要と認める事項": null,
        "受入対象者": null,
        "備考": ""
      }
    },
    {
      "type": "Feature",
      "geometry": {
        "type": "Point",
        "coordinates": [
          135.901507,
          35.611105
        ]
      },
      "properties": {
        "NO": 34405,
        "共通ID": "E1844200010111",
        "都道府県名及び市町村名": "福井県美浜町",
        "施設・場所名": "北西郷公民館",
        "住所": "福井県美浜町笹田15-1",
        "指定緊急避難場所との住所同一": "1",
        "その他市町村長が必要と認める事項": null,
        "受入対象者": null,
        "備考": ""
      }
    },
    {
      "type": "Feature",
      "geometry": {
        "type": "Point",
        "coordinates": [
          135.973306,
          35.563667
        ]
      },
      "properties": {
        "NO": 34406,
        "共通ID": "E1844200011111",
        "都道府県名及び市町村名": "福井県美浜町",
        "施設・場所名": "耳公民館新庄分館",
        "住所": "福井県美浜町新庄65-55",
        "指定緊急避難場所との住所同一": "1",
        "その他市町村長が必要と認める事項": null,
        "受入対象者": null,
        "備考": ""
      }
    },
    {
      "type": "Feature",
      "geometry": {
        "type": "Point",
        "coordinates": [
          135.977221,
          35.661571
        ]
      },
      "properties": {
        "NO": 34407,
        "共通ID": "E1844200012111",
        "都道府県名及び市町村名": "福井県美浜町",
        "施設・場所名": "山東公民館菅浜分館",
        "住所": "福井県美浜町菅浜70-8-2",
        "指定緊急避難場所との住所同一": "1",
        "その他市町村長が必要と認める事項": null,
        "受入対象者": null,
        "備考": ""
      }
    },
    {
      "type": "Feature",
      "geometry": {
        "type": "Point",
        "coordinates": [
          135.973759,
          35.706412
        ]
      },
      "properties": {
        "NO": 34408,
        "共通ID": "E1844200013111",
        "都道府県名及び市町村名": "福井県美浜町",
        "施設・場所名": "美浜町エネルギー環境教育体験館",
        "住所": "福井県美浜町丹生62-1",
        "指定緊急避難場所との住所同一": "1",
        "その他市町村長が必要と認める事項": null,
        "受入対象者": null,
        "備考": ""
      }
    },
    {
      "type": "Feature",
      "geometry": {
        "type": "Point",
        "coordinates": [
          135.949281,
          35.603884
        ]
      },
      "properties": {
        "NO": 34409,
        "共通ID": "E1844200014111",
        "都道府県名及び市町村名": "福井県美浜町",
        "施設・場所名": "美浜中学校",
        "住所": "福井県美浜町麻生37-5",
        "指定緊急避難場所との住所同一": "1",
        "その他市町村長が必要と認める事項": null,
        "受入対象者": null,
        "備考": ""
      }
    }
  ]
}