{
  "type": "FeatureCollection",
  "name": "206024",
  "features": [
    {
      "type": "Feature",
      "geometry": {
        "type": "Point",
        "coordinates": [
          138.574328,
          36.937501
        ]
      },
      "properties": {
        "NO": 38593,
        "共通ID": "E2060200079111",
        "都道府県名及び市町村名": "長野県栄村",
        "施設・場所名": "北野天満温泉",
        "住所": "長野県栄村堺14655",
        "指定緊急避難場所との住所同一": "",
        "その他市町村長が必要と認める事項": "",
        "受入対象者": "",
        "備考": ""
      }
    },
    {
      "type": "Feature",
      "geometry": {
        "type": "Point",
        "coordinates": [
          138.576251,
          36.988585
        ]
      },
      "properties": {
        "NO": 38594,
        "共通ID": "E2060200073121",
        "都道府県名及び市町村名": "長野県栄村",
        "施設・場所名": "栄村高齢者総合福祉センター",
        "住所": "長野県栄村大字北信3602",
        "指定緊急避難場所との住所同一": "",
        "その他市町村長が必要と認める事項": "",
        "受入対象者": "",
        "備考": ""
      }
    },
    {
      "type": "Feature",
      "geometry": {
        "type": "Point",
        "coordinates": [
          138.581851,
          36.989819
        ]
      },
      "properties": {
        "NO": 38595,
        "共通ID": "E2060200080111",
        "都道府県名及び市町村名": "長野県栄村",
        "施設・場所名": "栄中学校",
        "住所": "長野県栄村北信3892",
        "指定緊急避難場所との住所同一": "",
        "その他市町村長が必要と認める事項": "",
        "受入対象者": "",
        "備考": ""
      }
    }
  ]
}